{
  "fixed": [
    {
      "segment": "BASEBALL",
      "decisionCount": 64,
      "executedCount": 64,
      "wins": 37,
      "losses": 27,
      "stake": 64,
      "pnl": 20.89260208,
      "maximumSinglePositionContribution": 1.89855072,
      "roiPct": 32.64469075,
      "pnlSharePct": 56.27599949,
      "averageContribution": 0.32644691
    },
    {
      "segment": "TENNIS",
      "decisionCount": 4,
      "executedCount": 4,
      "wins": 4,
      "losses": 0,
      "stake": 4,
      "pnl": 6.23049588,
      "maximumSinglePositionContribution": 1.98507463,
      "roiPct": 155.762397,
      "pnlSharePct": 16.78237022,
      "averageContribution": 1.55762397
    },
    {
      "segment": "ICE HOCKEY",
      "decisionCount": 4,
      "executedCount": 4,
      "wins": 3,
      "losses": 1,
      "stake": 4,
      "pnl": 2.59460098,
      "maximumSinglePositionContribution": 1.4691358,
      "roiPct": 64.8650245,
      "pnlSharePct": 6.98877827,
      "averageContribution": 0.64865025
    },
    {
      "segment": "BASKETBALL",
      "decisionCount": 8,
      "executedCount": 8,
      "wins": 4,
      "losses": 4,
      "stake": 8,
      "pnl": 2.52621718,
      "maximumSinglePositionContribution": 2.07692308,
      "roiPct": 31.57771475,
      "pnlSharePct": 6.80458069,
      "averageContribution": 0.31577715
    },
    {
      "segment": "ESPORTS",
      "decisionCount": 1,
      "executedCount": 1,
      "wins": 1,
      "losses": 0,
      "stake": 1,
      "pnl": 1.98507463,
      "maximumSinglePositionContribution": 1.98507463,
      "roiPct": 198.507463,
      "pnlSharePct": 5.34696724,
      "averageContribution": 1.98507463
    },
    {
      "segment": "SOCCER",
      "decisionCount": 1,
      "executedCount": 1,
      "wins": 1,
      "losses": 0,
      "stake": 1,
      "pnl": 1.5974026,
      "maximumSinglePositionContribution": 1.5974026,
      "roiPct": 159.74026,
      "pnlSharePct": 4.30273968,
      "averageContribution": 1.5974026
    },
    {
      "segment": "UNRESOLVED",
      "decisionCount": 1,
      "executedCount": 1,
      "wins": 1,
      "losses": 0,
      "stake": 1,
      "pnl": 1.29885057,
      "maximumSinglePositionContribution": 1.29885057,
      "roiPct": 129.885057,
      "pnlSharePct": 3.49856441,
      "averageContribution": 1.29885057
    }
  ],
  "dynamic": [
    {
      "segment": "BASEBALL",
      "decisionCount": 64,
      "executedCount": 64,
      "wins": 37,
      "losses": 27,
      "stake": 79.67726792,
      "pnl": 27.2655893,
      "maximumSinglePositionContribution": 2.50712358,
      "roiPct": 34.22003542,
      "pnlSharePct": 61.91392836,
      "averageContribution": 0.42602483
    },
    {
      "segment": "TENNIS",
      "decisionCount": 4,
      "executedCount": 4,
      "wins": 4,
      "losses": 0,
      "stake": 4.471082,
      "pnl": 7.01111534,
      "maximumSinglePositionContribution": 2.34163558,
      "roiPct": 156.81026069,
      "pnlSharePct": 15.92064225,
      "averageContribution": 1.75277883
    },
    {
      "segment": "ICE HOCKEY",
      "decisionCount": 4,
      "executedCount": 4,
      "wins": 3,
      "losses": 1,
      "stake": 5.02068529,
      "pnl": 2.94319757,
      "maximumSinglePositionContribution": 1.73302334,
      "roiPct": 58.62143114,
      "pnlSharePct": 6.68332973,
      "averageContribution": 0.73579939
    },
    {
      "segment": "ESPORTS",
      "decisionCount": 1,
      "executedCount": 1,
      "wins": 1,
      "losses": 0,
      "stake": 1.04293943,
      "pnl": 2.0703126,
      "maximumSinglePositionContribution": 2.0703126,
      "roiPct": 198.5074627,
      "pnlSharePct": 4.70120725,
      "averageContribution": 2.0703126
    },
    {
      "segment": "BASKETBALL",
      "decisionCount": 8,
      "executedCount": 8,
      "wins": 4,
      "losses": 4,
      "stake": 10.05604208,
      "pnl": 1.69920415,
      "maximumSinglePositionContribution": 2.93680431,
      "roiPct": 16.89734526,
      "pnlSharePct": 3.85850468,
      "averageContribution": 0.21240052
    },
    {
      "segment": "UNRESOLVED",
      "decisionCount": 1,
      "executedCount": 1,
      "wins": 1,
      "losses": 0,
      "stake": 1.17962093,
      "pnl": 1.53215132,
      "maximumSinglePositionContribution": 1.53215132,
      "roiPct": 129.88505723,
      "pnlSharePct": 3.47916585,
      "averageContribution": 1.53215132
    },
    {
      "segment": "SOCCER",
      "decisionCount": 1,
      "executedCount": 1,
      "wins": 1,
      "losses": 0,
      "stake": 0.94924245,
      "pnl": 1.51632236,
      "maximumSinglePositionContribution": 1.51632236,
      "roiPct": 159.74026025,
      "pnlSharePct": 3.44322189,
      "averageContribution": 1.51632236
    }
  ]
}
